LICENSE
echo1_sma/__init__.py
echo1_sma/echo1_sma.py
echo1_sma-0.1.1.dist-info/LICENSE
echo1_sma-0.1.1.dist-info/WHEEL
echo1_sma-0.1.1.dist-info/METADATA
echo1_sma-0.1.1.dist-info/RECORD
